{
    "data": {
        "albumResults": [{
            "albumCover": "http://imagev2.xmcdn.com/group70/M03/BF/07/wKgO2F4ewUnyYhQYAANS29pomwY532.jpg!op_type=5&upload_type=album&device_type=ios&name=large&magick=png",
            "albumId": 32481716,
            "albumTitle": "我在皇宫当巨巨2",
            "avatar": "http://fdfs.xmcdn.com/group67/M05/8A/EC/wKgMbV2_5U-gwbGSAAC4gTDcYtE677_mobile_small.jpg",
            "dynamicType": 1,
            "isDraft": false,
            "isPaid": false,
            "isTop": false,
            "lastUpdateAt": 1583038802000,
            "nickname": "哔哩哔哩漫画",
            "preferredType": 0,
            "serialState": 1,
            "status": 1,
            "timeline": 1.599745492E13,
            "trackId": 261381689,
            "trackSellingPoints": [{
                "color": "4990E2",
                "text": "精品视频"
            }],
            "trackTitle": "我在皇宫当巨巨2 第十集 依依也想上画册",
            "trackType": 1,
            "uid": 12312356,
            "unreadNum": 0
        }, {
            "albumCover": "http://imagev2.xmcdn.com/group85/M00/80/90/wKg5H18yBkrhYpS2AAoPT8BCJOs500.jpg!op_type=5&upload_type=album&device_type=ios&name=large&magick=png",
            "albumId": 40757445,
            "albumTitle": "辽沈先声第2季",
            "avatar": "http://fdfs.xmcdn.com/group61/M01/A8/9D/wKgMcF2hLJ7Qz6y5AAAefU6a98823_mobile_small.jpeg",
            "dynamicType": 1,
            "isDraft": false,
            "isPaid": false,
            "isTop": false,
            "lastUpdateAt": 1600393056000,
            "nickname": "辽沈晚报",
            "preferredType": 0,
            "serialState": 1,
            "status": 1,
            "timeline": 1.600393056E13,
            "trackId": 337633374,
            "trackTitle": "大谈“导师崇高师娘优美”论文作者被处理：追回已拨项目资金",
            "trackType": 1,
            "uid": 164589257,
            "unreadNum": 99,
            "vipFreeType": 0
        }, {
            "albumCover": "http://imagev2.xmcdn.com/group87/M03/89/0E/wKg5IV8C0JeiGm4qAA5a07ycr1k544.png!op_type=5&upload_type=album&device_type=ios&name=large&magick=png",
            "albumId": 39581929,
            "albumSubscript": "{\"albumSubscriptValue\":1}",
            "albumTitle": "此刻中国",
            "avatar": "http://fdfs.xmcdn.com/group80/M07/19/1D/wKgPDF7U2CvR5NaNAAE1GUT6uKo878_mobile_small.jpg",
            "dynamicType": 1,
            "isDraft": false,
            "isPaid": false,
            "isTop": false,
            "lastUpdateAt": 1600335226000,
            "nickname": "胡辣汤fm",
            "preferredType": 1,
            "serialState": 0,
            "status": 1,
            "timeline": 1.600335226E13,
            "trackId": 337434853,
            "trackTitle": "张玉环向三部委提交控告材料，请求追责16名公检法办案人员",
            "trackType": 1,
            "uid": 238249517,
            "unreadNum": 51
        }, {
            "albumCover": "http://imagev2.xmcdn.com/group83/M02/80/E1/wKg5I18ai7XTJs2UAAJrB9zCeFw605.jpg!op_type=5&upload_type=album&device_type=ios&name=large&magick=png",
            "albumId": 40195185,
            "albumSubscript": "{\"albumSubscriptValue\":2}",
            "albumTitle": "鬼谷子权谋之本丨识人读心术",
            "avatar": "http://fdfs.xmcdn.com/group71/M06/33/8D/wKgO2V4VdEHBVag7AAGP7RZNo5A98_mobile_small.jpeg",
            "dynamicType": 1,
            "isAuthorized": false,
            "isDraft": false,
            "isPaid": true,
            "isTop": false,
            "isVipFree": true,
            "lastUpdateAt": 1600340408000,
            "nickname": "娱悦佳音",
            "preferredType": 0,
            "serialState": 1,
            "status": 1,
            "timeline": 1.600340408E13,
            "trackId": 337459670,
            "trackTitle": "46.莫知所为，退为大仪—忠言也可以很顺耳",
            "trackType": 1,
            "uid": 135579251,
            "unreadNum": 8,
            "vipFreeType": 0
        }, {
            "albumCover": "http://imagev2.xmcdn.com/group73/M06/D5/EE/wKgO0V5ltZDDpXzhAA_85RO57d0562.png!op_type=5&upload_type=album&device_type=ios&name=large&magick=png",
            "albumId": 34968559,
            "albumTitle": "鬼谷子全集|国学谋略必听经典",
            "avatar": "http://fdfs.xmcdn.com/group64/M02/4D/13/wKgMaV1jq3fwYI-NAAHWI4S93h0985_mobile_small.png",
            "dynamicType": 1,
            "isDraft": false,
            "isPaid": false,
            "isTop": false,
            "lastUpdateAt": 1600392756000,
            "nickname": "鬼谷子全集",
            "preferredType": 0,
            "serialState": 0,
            "status": 1,
            "timeline": 1.600392756E13,
            "trackId": 337632223,
            "trackTitle": "113、第十二章符篇第十二之把准调查询问的原则（下）",
            "trackType": 1,
            "uid": 185401137,
            "unreadNum": 18
        }, {
            "albumCover": "http://imagev2.xmcdn.com/group76/M02/9C/C8/wKgO1F6R3XfT9A-lAADfY4obI_w762.jpg!op_type=5&upload_type=album&device_type=ios&name=large&magick=png",
            "albumId": 32062140,
            "albumTitle": "鬼谷子全集丨中国人智慧第一课",
            "avatar": "http://fdfs.xmcdn.com/group67/M0A/BD/3D/wKgMbV3xL1yAJZTuAABHVU9wbJM72_mobile_small.jpeg",
            "dynamicType": 1,
            "isDraft": false,
            "isPaid": false,
            "isTop": false,
            "lastUpdateAt": 1600344780000,
            "nickname": "成鹤子云",
            "preferredType": 0,
            "serialState": 1,
            "status": 1,
            "timeline": 1.60039152E13,
            "trackId": 337487232,
            "trackTitle": "511为什么说，美貌也是一种福报",
            "trackType": 1,
            "uid": 158302101,
            "unreadNum": 39
        }, {
            "albumCover": "http://imagev2.xmcdn.com/group87/M0B/3F/2B/wKg5IV8U5vHRwcOmAAaB23EJjXE262.png!op_type=5&upload_type=album&device_type=ios&name=large&magick=png",
            "albumId": 39489029,
            "albumTitle": "鬼谷子全集",
            "avatar": "http://fdfs.xmcdn.com/group86/M0B/58/A1/wKg5IF8W1HWSkDf4AAJhVQpY_Z0357_mobile_small.png",
            "dynamicType": 1,
            "isDraft": false,
            "isPaid": false,
            "isTop": false,
            "lastUpdateAt": 1600391297000,
            "nickname": "国学经典之声",
            "preferredType": 0,
            "serialState": 0,
            "status": 1,
            "timeline": 1.600391297E13,
            "trackId": 337627344,
            "trackTitle": "103、鬼谷子全集",
            "trackType": 1,
            "uid": 238809650,
            "unreadNum": 10
        }, {
            "albumCover": "http://imagev2.xmcdn.com/group85/M0A/88/51/wKg5H18a6vCR__PRAAa5NPa_KcI193.jpg!op_type=5&upload_type=album&device_type=ios&name=large&magick=png",
            "albumId": 40161763,
            "albumTitle": "鬼谷子：心灵解惑手册",
            "avatar": "http://fdfs.xmcdn.com/group67/M0A/BD/3D/wKgMbV3xL1yAJZTuAABHVU9wbJM72_mobile_small.jpeg",
            "dynamicType": 1,
            "isDraft": false,
            "isPaid": false,
            "isTop": false,
            "lastUpdateAt": 1600391280000,
            "nickname": "成鹤子云",
            "preferredType": 0,
            "serialState": 1,
            "status": 1,
            "timeline": 1.60039128E13,
            "trackId": 337627288,
            "trackTitle": "315 为什么说婚姻就如通投资（下）",
            "trackType": 1,
            "uid": 158302101,
            "unreadNum": 39
        }, {
            "albumCover": "http://imagev2.xmcdn.com/group86/M05/7D/8F/wKg5IF8aM1ii8S-eAADoLtA2Qtk246.jpg!op_type=5&upload_type=album&device_type=ios&name=large&magick=png",
            "albumId": 39796060,
            "albumTitle": "中国古典纯音乐 — 禅意静心",
            "avatar": "http://fdfs.xmcdn.com/group58/M03/4A/0D/wKgLgl3yJDaBmpRyAABm6mOS19w808_mobile_small.jpg",
            "dynamicType": 1,
            "isDraft": false,
            "isPaid": false,
            "isTop": false,
            "lastUpdateAt": 1600389723000,
            "nickname": "雪儿XueEr",
            "preferredType": 0,
            "serialState": 0,
            "status": 1,
            "timeline": 1.600389723E13,
            "trackId": 337622302,
            "trackTitle": "秋瑟",
            "trackType": 1,
            "uid": 60886707,
            "unreadNum": 14
        }, {
            "albumCover": "http://imagev2.xmcdn.com/group87/M06/CF/8D/wKg5IV8J4BqwW176AADCqhzNeqs564.jpg!op_type=5&upload_type=album&device_type=ios&name=large&magick=png",
            "albumId": 39762979,
            "albumTitle": "鬼谷子：白话全说",
            "avatar": "http://fdfs.xmcdn.com/group85/M05/D2/5A/wKg5H18J34ji6afYAACISYqn5bM646_mobile_small.jpg",
            "dynamicType": 1,
            "isDraft": false,
            "isPaid": false,
            "isTop": false,
            "lastUpdateAt": 1600389240000,
            "nickname": "尊易国学",
            "preferredType": 0,
            "serialState": 1,
            "status": 1,
            "timeline": 1.60038924E13,
            "trackId": 337621334,
            "trackTitle": "404桃花劫从哪里来？（下）",
            "trackType": 1,
            "uid": 112911150,
            "unreadNum": 47
        }, {
            "albumCover": "http://imagev2.xmcdn.com/group82/M07/37/51/wKg5HF7fFrTjaJTuAAFnGD2JtEs313.jpg!op_type=5&upload_type=album&device_type=ios&name=large&magick=png",
            "albumId": 38779547,
            "albumTitle": "经典重现 丨 怀旧老歌",
            "avatar": "http://fdfs.xmcdn.com/group77/M0B/89/3A/wKgO1V5waR_BsmyyAACwGxG6QGc199_mobile_small.jpg",
            "dynamicType": 1,
            "isDraft": false,
            "isPaid": false,
            "isTop": false,
            "lastUpdateAt": 1600387688000,
            "nickname": "司司_读书吧",
            "preferredType": 0,
            "serialState": 1,
            "status": 1,
            "timeline": 1.600387688E13,
            "trackId": 337617930,
            "trackTitle": "【音乐】纯乐丨片头音乐 (45)",
            "trackType": 1,
            "uid": 183757566,
            "unreadNum": 99
        }, {
            "albumCover": "http://imagev2.xmcdn.com/group83/M08/53/AF/wKg5HV8tcl-TjFhVAAU1JX7dOT0282.jpg!op_type=5&upload_type=album&device_type=ios&name=large&magick=png",
            "albumId": 40511197,
            "albumTitle": "即刻松绑：宁静温暖的治愈系轻音乐",
            "avatar": "http://fdfs.xmcdn.com/group85/M06/56/C7/wKg5JV8Wrpqx7vwTAACtULcFT2M360_mobile_small.jpg",
            "dynamicType": 1,
            "isDraft": false,
            "isPaid": false,
            "isTop": false,
            "lastUpdateAt": 1600382460000,
            "nickname": "音抚",
            "preferredType": 0,
            "serialState": 1,
            "status": 1,
            "timeline": 1.60038246E13,
            "trackId": 337599360,
            "trackTitle": "音符疗愈｜星星点点",
            "trackType": 1,
            "uid": 85619462,
            "unreadNum": 2
        }, {
            "albumCover": "http://imagev2.xmcdn.com/group82/M02/58/EB/wKg5Il79dwbg1-MwAAIMDpfs9Pg371.jpg!op_type=5&upload_type=album&device_type=ios&name=large&magick=png",
            "albumId": 39454341,
            "albumTitle": "白日梦我 |青春纯爱 |双播",
            "avatar": "http://fdfs.xmcdn.com/group41/M06/FC/62/wKgJ8VqdRP6jg_PVAAEZLVW1Lx0087_mobile_small.jpg",
            "dynamicType": 1,
            "isDraft": false,
            "isPaid": false,
            "isTop": false,
            "lastUpdateAt": 1600380360000,
            "nickname": "方姣姣",
            "preferredType": 0,
            "serialState": 0,
            "status": 1,
            "timeline": 1.60038036E13,
            "trackId": 337595576,
            "trackTitle": "白日梦我111",
            "trackType": 1,
            "uid": 60906922,
            "unreadNum": 9
        }, {
            "albumCover": "http://imagev2.xmcdn.com/group84/M04/BA/33/wKg5Hl83QeuTiuQyAASEEzuTMVk269.jpg!op_type=5&upload_type=album&device_type=ios&name=large&magick=png",
            "albumId": 38704668,
            "albumTitle": "催眠下雨声‖助眠音乐催眠曲",
            "avatar": "http://fdfs.xmcdn.com/group80/M02/4D/D8/wKgPEV63Xn3Q8MMtAACgS97GUXI866_mobile_small.jpg",
            "dynamicType": 1,
            "isDraft": false,
            "isPaid": false,
            "isTop": false,
            "lastUpdateAt": 1600360980000,
            "nickname": "波涛之声",
            "preferredType": 0,
            "serialState": 1,
            "status": 1,
            "timeline": 1.60036098E13,
            "trackId": 337587599,
            "trackTitle": "催眠下雨声-助眠音乐-下雨天钢琴曲系列之女儿情",
            "trackType": 1,
            "uid": 206455451,
            "unreadNum": 8
        }, {
            "albumCover": "http://imagev2.xmcdn.com/group83/M05/5C/0F/wKg5I18XAKKxOTX8ABffOVmxSs4530.png!op_type=5&upload_type=album&device_type=ios&name=large&magick=png",
            "albumId": 40109836,
            "albumTitle": "鬼谷子的智慧谋略",
            "avatar": "http://fdfs.xmcdn.com/group40/M0A/10/1A/wKgJT1qgpuvC5mNxAAtmuRQl7VY085_mobile_small.png",
            "dynamicType": 1,
            "isDraft": false,
            "isPaid": false,
            "isTop": false,
            "lastUpdateAt": 1600359242000,
            "nickname": "江南易林周易研究中心",
            "preferredType": 0,
            "serialState": 1,
            "status": 1,
            "timeline": 1.600359242E13,
            "trackId": 337585064,
            "trackTitle": "24、权篇： 看穿5种虚假的言辞，避免上当受骗【2】",
            "trackType": 1,
            "uid": 107302047,
            "unreadNum": 28
        }, {
            "albumCover": "http://imagev2.xmcdn.com/group74/M09/32/8E/wKgO0l58F4Cjo1P-AACk1brG5lI654.jpg!op_type=5&upload_type=album&device_type=ios&name=large&magick=png",
            "albumId": 35516850,
            "albumSubscript": "{\"albumSubscriptValue\":2}",
            "albumTitle": "鬼谷子权谋智慧：从零学为人处世",
            "avatar": "http://fdfs.xmcdn.com/group55/M0A/75/D3/wKgLdVyTQnzTj13MAADJJLiupmQ883_mobile_small.jpg",
            "dynamicType": 1,
            "isAuthorized": false,
            "isDraft": false,
            "isPaid": true,
            "isTop": false,
            "isVipFree": false,
            "lastUpdateAt": 1600358451000,
            "nickname": "小鸟文化",
            "preferredType": 0,
            "serialState": 1,
            "status": 1,
            "timeline": 1.600358446E13,
            "trackId": 337583218,
            "trackTitle": "254 做人最高级的智慧，是懂得独立思考，理性判断(3)",
            "trackType": 1,
            "uid": 29317018,
            "unreadNum": 36,
            "vipFreeType": 1
        }, {
            "albumCover": "http://imagev2.xmcdn.com/group87/M09/85/FD/wKg5J18a7-OjSsi-AAa2gqsDUIE539.jpg!op_type=5&upload_type=album&device_type=ios&name=large&magick=png",
            "albumId": 39248127,
            "albumTitle": "鬼谷子之谜",
            "avatar": "http://fdfs.xmcdn.com/group56/M00/93/97/wKgLdlyUpdXC5wacAAEI1ZrAQxY700_mobile_small.jpg",
            "dynamicType": 1,
            "isDraft": false,
            "isPaid": false,
            "isTop": false,
            "lastUpdateAt": 1600352161000,
            "nickname": "哲思睿慧",
            "preferredType": 0,
            "serialState": 1,
            "status": 1,
            "timeline": 1.600352161E13,
            "trackId": 337550949,
            "trackTitle": "341橙子的故事（三）",
            "trackType": 1,
            "uid": 87713766,
            "unreadNum": 23
        }, {
            "albumCover": "http://imagev2.xmcdn.com/group82/M0A/10/DF/wKg5Il8_dgfQHb2rAANZKxy2aQk907.png!op_type=5&upload_type=album&device_type=ios&name=large&magick=png",
            "albumId": 40677640,
            "albumTitle": "记忆提升阿尔法α脑波音乐|增强记忆力",
            "avatar": "http://fdfs.xmcdn.com/group83/M09/9A/FF/wKg5HV9LsL-Sv81qAAEpZMNLF6Q632_mobile_small.jpg",
            "dynamicType": 1,
            "isDraft": false,
            "isPaid": false,
            "isTop": false,
            "lastUpdateAt": 1600261208000,
            "nickname": "记忆提升小达人",
            "preferredType": 0,
            "serialState": 1,
            "status": 1,
            "timeline": 1.600347606E13,
            "trackId": 337215863,
            "trackTitle": "46行动力增强α脑波音乐（提高记忆力、专注力、睡眠、情商、食欲、缓解压力）",
            "trackType": 1,
            "uid": 248513774,
            "unreadNum": 7
        }, {
            "albumCover": "http://imagev2.xmcdn.com/group82/M01/3A/B0/wKg5Il8URoWQiIgNAAqLQcL2TN8893.jpg!op_type=5&upload_type=album&device_type=ios&name=large&magick=png",
            "albumId": 40034123,
            "albumTitle": "宝宝经典儿歌|0~6岁",
            "avatar": "http://fdfs.xmcdn.com/group84/M0B/B7/CC/wKg5Hl82xyfDJu9XAAC7yVhwHEM063_mobile_small.jpg",
            "dynamicType": 1,
            "isDraft": false,
            "isPaid": false,
            "isTop": false,
            "lastUpdateAt": 1600341939000,
            "nickname": "小红帽FM_",
            "preferredType": 0,
            "serialState": 1,
            "status": 1,
            "timeline": 1.600341939E13,
            "trackId": 337469336,
            "trackTitle": "摇篮曲",
            "trackType": 1,
            "uid": 97280200,
            "unreadNum": 14
        }, {
            "albumCover": "http://imagev2.xmcdn.com/group75/M0B/80/70/wKgO3V5PdOnyOQaxAA1Ti2kvMWo440.jpg!op_type=5&upload_type=album&device_type=ios&name=large&magick=png",
            "albumId": 26308391,
            "albumSubscript": "{\"albumSubscriptValue\":4}",
            "albumTitle": "「限时免费」少儿英语启蒙课·牛津树（5天）",
            "avatar": "http://fdfs.xmcdn.com/group60/M05/21/B1/wKgLb1ytvzLyM9buAAH1BRKXYeU574_mobile_small.png",
            "dynamicType": 1,
            "isAuthorized": true,
            "isDraft": false,
            "isPaid": true,
            "isTop": false,
            "isVipFree": false,
            "lastUpdateAt": 1580369037000,
            "nickname": "奇妙英语",
            "preferredType": 0,
            "serialState": 2,
            "status": 1,
            "timeline": 1.60033323E13,
            "trackId": 247827315,
            "trackTitle": "【抗疫特别策划】05 出门一定戴“好”口罩！",
            "trackType": 1,
            "uid": 147770569,
            "unreadNum": 0,
            "vipFreeType": 0
        }, {
            "albumCover": "http://imagev2.xmcdn.com/group82/M01/72/EB/wKg5HF8xAkqCuB4iAAjUAYgDVKA51.jpeg!op_type=5&upload_type=album&device_type=ios&name=large&magick=png",
            "albumId": 40732940,
            "albumTitle": "人民网新闻",
            "avatar": "http://fdfs.xmcdn.com/group80/M04/E2/37/wKgPEV6zi7ezPyzlAAAiPVXtjkI224_mobile_small.jpg",
            "dynamicType": 1,
            "isDraft": false,
            "isPaid": false,
            "isTop": false,
            "lastUpdateAt": 1600330800000,
            "nickname": "人民网新闻",
            "preferredType": 0,
            "serialState": 0,
            "status": 1,
            "timeline": 1.6003308E13,
            "trackId": 337420549,
            "trackTitle": "市场监管总局：网售江西井冈绿宝公司产纯香稻米油等5批次食品不合格",
            "trackType": 1,
            "uid": 155311240,
            "unreadNum": 60
        }, {
            "albumCover": "http://imagev2.xmcdn.com/group85/M03/3D/F1/wKg5H18rvrfwtY6xAAKQcVmBxlM092.png!op_type=5&upload_type=album&device_type=ios&name=large&magick=png",
            "albumId": 40610972,
            "albumTitle": "《晚安|治愈你每一个失眠的夜晚》-纯音乐",
            "avatar": "http://fdfs.xmcdn.com/group83/M09/27/36/wKg5I19YrS2xxoKOAACZ--M-9mg235_mobile_small.jpg",
            "dynamicType": 1,
            "isDraft": false,
            "isPaid": false,
            "isTop": false,
            "lastUpdateAt": 1600314218000,
            "nickname": "沙皮_oo",
            "preferredType": 0,
            "serialState": 0,
            "status": 1,
            "timeline": 1.600314218E13,
            "trackId": 337367286,
            "trackTitle": "沙皮 - 亲爱的，黎明还没来！",
            "trackType": 1,
            "uid": 86778546,
            "unreadNum": 2
        }, {
            "albumCover": "http://imagev2.xmcdn.com/group87/M05/7B/3E/wKg5IV9geqqiGC_MAAZLhqF34do716.jpg!op_type=5&upload_type=album&device_type=ios&name=large&magick=png",
            "albumId": 39952843,
            "albumSubscript": "{\"albumSubscriptValue\":2}",
            "albumTitle": "《狼道：生活中的狼性法则》正版大全集 | 2020全新升级版",
            "avatar": "http://fdfs.xmcdn.com/group47/M04/9A/B5/wKgKk1uSFz3REpNOAAEEH5y3z2o281_mobile_small.jpg",
            "dynamicType": 1,
            "isAuthorized": false,
            "isDraft": false,
            "isPaid": true,
            "isTop": false,
            "isVipFree": false,
            "lastUpdateAt": 1600293609000,
            "nickname": "大吕说书",
            "preferredType": 0,
            "serialState": 1,
            "status": 1,
            "timeline": 1.600293609E13,
            "trackId": 337306507,
            "trackTitle": "062 在目标恒定中专心致志4",
            "trackType": 1,
            "uid": 125299064,
            "unreadNum": 11,
            "vipFreeType": 1
        }, {
            "albumCover": "http://imagev2.xmcdn.com/group82/M06/7B/E3/wKg5HF8aSt_TVWw3AAG7BWYIEms351.jpg!op_type=5&upload_type=album&device_type=ios&name=large&magick=png",
            "albumId": 39879763,
            "albumSubscript": "{\"albumSubscriptValue\":2}",
            "albumTitle": "卡耐基人性大合集（古典乐精制版）| 人性的弱点，人性的优点",
            "avatar": "http://fdfs.xmcdn.com/group73/M02/8F/70/wKgO0V6RqYGiacCpAAKNssLfaBc598_mobile_small.jpg",
            "dynamicType": 1,
            "isAuthorized": false,
            "isDraft": false,
            "isPaid": true,
            "isTop": false,
            "isVipFree": false,
            "lastUpdateAt": 1600250449000,
            "nickname": "苍海一飞鸿",
            "preferredType": 0,
            "serialState": 1,
            "status": 1,
            "timeline": 1.600250449E13,
            "trackId": 337130684,
            "trackTitle": "《人性的弱点》45 家庭幸福美满的规则二：不要试图改造对方",
            "trackType": 1,
            "uid": 59647967,
            "unreadNum": 7,
            "vipFreeType": 1
        }, {
            "albumCover": "http://imagev2.xmcdn.com/group86/M03/1C/6D/wKg5Jl8_-2fSyUnmAAFB8NnQR8E782.jpg!op_type=5&upload_type=album&device_type=ios&name=large&magick=png",
            "albumId": 39732147,
            "albumTitle": "神秘太阳系｜真正到宇宙科学",
            "avatar": "http://fdfs.xmcdn.com/group84/M07/78/E8/wKg5JF9f_-3h7ORIAAHDBuiUh1k757_mobile_small.jpg",
            "dynamicType": 1,
            "isDraft": false,
            "isPaid": false,
            "isTop": false,
            "lastUpdateAt": 1600246590000,
            "nickname": "弓长鼑人",
            "preferredType": 0,
            "serialState": 0,
            "status": 1,
            "timeline": 1.60024659E13,
            "trackId": 337114903,
            "trackTitle": "第六十五集 史前核反应堆之谜",
            "trackType": 1,
            "uid": 137717277,
            "unreadNum": 2
        }, {
            "albumCover": "http://imagev2.xmcdn.com/group83/M08/5C/92/wKg5HV9GJwyAuEOxAAXbZyWhDb0791.jpg!op_type=5&upload_type=album&device_type=ios&name=large&magick=png",
            "albumId": 39643180,
            "albumTitle": "治疗师 | 助眠解压3D环绕体验",
            "avatar": "http://fdfs.xmcdn.com/group85/M09/43/8D/wKg5H1768gSwbhf_AAQtWQC5Nzc038_mobile_small.jpg",
            "dynamicType": 1,
            "isDraft": false,
            "isPaid": false,
            "isTop": false,
            "lastUpdateAt": 1600186801000,
            "nickname": "三火Producer",
            "preferredType": 0,
            "serialState": 0,
            "status": 1,
            "timeline": 1.600186801E13,
            "trackId": 336978967,
            "trackTitle": "坠入星河",
            "trackType": 1,
            "uid": 48566710,
            "unreadNum": 2
        }, {
            "albumCover": "http://imagev2.xmcdn.com/group67/M01/27/7E/wKgMbV25jQ3xd580AABS1CnsVgI067.jpg!op_type=5&upload_type=album&device_type=ios&name=large&magick=png",
            "albumId": 30586083,
            "albumTitle": "金瓶梅（国家一级播音员免费版）",
            "avatar": "http://fdfs.xmcdn.com/group47/M01/03/8F/wKgKk1uGJ1PjsejLAAGlgXugw6k488_mobile_small.jpg",
            "dynamicType": 1,
            "isDraft": false,
            "isPaid": false,
            "isTop": false,
            "lastUpdateAt": 1600177816000,
            "nickname": "说书的小马哥",
            "preferredType": 0,
            "serialState": 1,
            "status": 1,
            "timeline": 1.600177816E13,
            "trackId": 336931913,
            "trackTitle": "评点金瓶（72）明代：一个好官的标准",
            "trackType": 1,
            "uid": 41986502,
            "unreadNum": 2
        }, {
            "albumCover": "http://imagev2.xmcdn.com/group84/M0A/01/B9/wKg5Hl7Z1z7DYRfLAARSjWL0kEE878.jpg!op_type=5&upload_type=album&device_type=ios&name=large&magick=png",
            "albumId": 38567236,
            "albumTitle": "入眠率99％ 超长高清稀有音频",
            "avatar": "http://fdfs.xmcdn.com/group65/M00/E6/7A/wKgMal2AfGnTBbVhAAD3ZtT7c8c041_mobile_small.jpg",
            "dynamicType": 1,
            "isDraft": false,
            "isPaid": false,
            "isTop": false,
            "lastUpdateAt": 1600172880000,
            "nickname": "逸声_瘦瘦",
            "preferredType": 0,
            "serialState": 1,
            "status": 1,
            "timeline": 1.60017288E13,
            "trackId": 336872255,
            "trackTitle": "30分钟 大自然催眠曲秘境森林",
            "trackType": 1,
            "uid": 27403003,
            "unreadNum": 5
        }, {
            "albumCover": "http://imagev2.xmcdn.com/group83/M00/B5/CD/wKg5HV8fnwDj9W0yAAZEIwv6HsI297.jpg!op_type=5&upload_type=album&device_type=ios&name=large&magick=png",
            "albumId": 40092644,
            "albumSubscript": "{\"albumSubscriptValue\":2}",
            "albumTitle": "空灵东方禅乐｜解压疗愈音乐",
            "avatar": "http://fdfs.xmcdn.com/group84/M06/FA/86/wKg5Hl7yw1CBcWa3AAIqZipmZxw235_mobile_small.jpg",
            "dynamicType": 1,
            "isAuthorized": false,
            "isDraft": false,
            "isPaid": true,
            "isTop": false,
            "isVipFree": false,
            "lastUpdateAt": 1600164006000,
            "nickname": "叶云川的瑞鸣音乐台",
            "preferredType": 0,
            "serialState": 1,
            "status": 1,
            "timeline": 1.600164006E13,
            "trackId": 336805974,
            "trackTitle": "平沙落雁（唐琴版）",
            "trackType": 1,
            "uid": 48242388,
            "unreadNum": 10,
            "vipFreeType": 1
        }, {
            "albumCover": "http://imagev2.xmcdn.com/group85/M00/D4/0F/wKg5H18iMjbz3RiwAAKsgAP5Ef070.jpeg!op_type=5&upload_type=album&device_type=ios&name=large&magick=png",
            "albumId": 40198127,
            "albumSubscript": "{\"albumSubscriptValue\":2}",
            "albumTitle": "颂钵冥想｜体验自然万物的声音密码",
            "avatar": "http://fdfs.xmcdn.com/group45/M08/71/1E/wKgKlFtn_geDHsaYAABycHq5Wx4954_mobile_small.jpg",
            "dynamicType": 1,
            "isAuthorized": false,
            "isDraft": false,
            "isPaid": true,
            "isTop": false,
            "isVipFree": true,
            "lastUpdateAt": 1600077895000,
            "nickname": "雨法雨音乐",
            "preferredType": 0,
            "serialState": 1,
            "status": 1,
            "timeline": 1.600077895E13,
            "trackId": 336487960,
            "trackTitle": "水滴冥想｜净化思绪杂质，专注聆听水滴声音",
            "trackType": 1,
            "uid": 40365723,
            "unreadNum": 2,
            "vipFreeType": 0
        }],
        "hasMore": true,
        "totalSize": 68
    },
    "ret": 0
}
